ecapture/__init__.py
ecapture/ecapture.py
ecapture-2.0.2.data/scripts/ecapture.py
ecapture-2.0.2.dist-info/License.txt
ecapture-2.0.2.dist-info/METADATA
ecapture-2.0.2.dist-info/WHEEL
ecapture-2.0.2.dist-info/top_level.txt
ecapture-2.0.2.dist-info/RECORD
