Metadata-Version: 2.1
Name: ecapture
Version: 2.0.2
Summary: Webcams made easy
Home-page: https://github.com/YFOMNN/ecapture
Author: Mohammmed Yaseen
Author-email: hmyaseen05@gmail.com
License: GNU GPLv3
Classifier: License :: OSI Approved :: GNU General Public License v3 (GPLv3)
Classifier: Programming Language :: Python :: 3
License-File: License.txt
